{
  "hideStrictPathFilters": true,
  "pinFilters": {
    "active": true,
    "tags": [
      {
        "name": "",
        "active": true,
        "pattern": "",
        "patternType": "STRICT"
      }
    ],
    "paths": [
      {
        "name": "",
        "active": true,
        "type": "FILES_AND_DIRECTORIES",
        "pattern": "",
        "patternType": "WILDCARD"
      }
    ],
    "frontMatter": [
      {
        "name": "",
        "active": true,
        "path": "",
        "pattern": "",
        "patternType": "STRICT"
      }
    ]
  },
  "hideFilters": {
    "active": false,
    "tags": [
      {
        "name": "",
        "active": true,
        "pattern": "",
        "patternType": "STRICT"
      }
    ],
    "paths": [
      {
        "name": "",
        "active": true,
        "type": "FILES_AND_DIRECTORIES",
        "pattern": "",
        "patternType": "WILDCARD"
      },
      {
        "name": "",
        "active": true,
        "type": "FILES",
        "pattern": "_templates/datetime-code.md",
        "patternType": "STRICT"
      },
      {
        "name": "",
        "active": true,
        "type": "FILES",
        "pattern": "_templates/emoji-set.md",
        "patternType": "STRICT"
      },
      {
        "name": "",
        "active": true,
        "type": "FILES",
        "pattern": "_templates/header-json-demoblog.md",
        "patternType": "STRICT"
      },
      {
        "name": "",
        "active": true,
        "type": "FILES",
        "pattern": "_templates/header-simple.md",
        "patternType": "STRICT"
      },
      {
        "name": "",
        "active": true,
        "type": "FILES",
        "pattern": "_templates/insert-notes.md",
        "patternType": "STRICT"
      },
      {
        "name": "",
        "active": true,
        "type": "FILES",
        "pattern": "_templates/document_tail-json-simp.md",
        "patternType": "STRICT"
      },
      {
        "name": "",
        "active": true,
        "type": "FILES",
        "pattern": "_templates/document_header-json-simp.md",
        "patternType": "STRICT"
      }
    ],
    "frontMatter": [
      {
        "name": "",
        "active": true,
        "path": "",
        "pattern": "",
        "patternType": "STRICT"
      }
    ]
  }
}